yajs/__init__.py
yajs/lib.py
yajs/libyajl.dylib
yajs/libyajl.so
yajs/tokenizer.py
yajs-1.0.2.dist-info/DESCRIPTION.rst
yajs-1.0.2.dist-info/METADATA
yajs-1.0.2.dist-info/RECORD
yajs-1.0.2.dist-info/WHEEL
yajs-1.0.2.dist-info/metadata.json
yajs-1.0.2.dist-info/top_level.txt
