Metadata-Version: 2.0
Name: yajs
Version: 1.0.2
Summary: A small wrapper around YAJL's lexer
Home-page: https://github.com/fireteam/yajs
Author: Fireteam Ltd.
Author-email: info@fireteam.net
License: BSD
Platform: UNKNOWN
Classifier: Development Status :: 5 - Production/Stable
Classifier: Environment :: Web Environment
Classifier: Intended Audience :: Developers
Classifier: License :: OSI Approved :: BSD License
Classifier: Programming Language :: Python
